code2prompt/__init__.py
code2prompt/commands/__init__.py
code2prompt/commands/analyze.py
code2prompt/commands/base_command.py
code2prompt/commands/generate.py
code2prompt/commands/interactive_selector.py
code2prompt/comment_stripper/__init__.py
code2prompt/comment_stripper/c_style.py
code2prompt/comment_stripper/html_style.py
code2prompt/comment_stripper/matlab_style.py
code2prompt/comment_stripper/python_style.py
code2prompt/comment_stripper/r_style.py
code2prompt/comment_stripper/shell_style.py
code2prompt/comment_stripper/sql_style.py
code2prompt/comment_stripper/strip_comments.py
code2prompt/config.py
code2prompt/core/__init__.py
code2prompt/core/file_path_retriever.py
code2prompt/core/generate_content.py
code2prompt/core/process_file.py
code2prompt/core/process_files.py
code2prompt/core/template_processor.py
code2prompt/core/write_output.py
code2prompt/data/token_price.json
code2prompt/main.py
code2prompt/print_help.py
code2prompt/templates/analyze-code.j2
code2prompt/templates/code-review.j2
code2prompt/templates/create-function.j2
code2prompt/templates/create-readme.j2
code2prompt/templates/default.j2
code2prompt/templates/improve-this-prompt.j2
code2prompt/utils/add_line_numbers.py
code2prompt/utils/analyzer.py
code2prompt/utils/config.py
code2prompt/utils/count_tokens.py
code2prompt/utils/create_template_directory.py
code2prompt/utils/display_price_table.py
code2prompt/utils/file_utils.py
code2prompt/utils/generate_markdown_content.py
code2prompt/utils/get_gitignore_patterns.py
code2prompt/utils/include_loader.py
code2prompt/utils/is_binary.py
code2prompt/utils/is_filtered.py
code2prompt/utils/is_ignored.py
code2prompt/utils/language_inference.py
code2prompt/utils/logging_utils.py
code2prompt/utils/output_utils.py
code2prompt/utils/parse_gitignore.py
code2prompt/utils/price_calculator.py
code2prompt/utils/should_process_file.py
code2prompt/version.py
code2prompt-0.8.0.dist-info/LICENCE.md
code2prompt-0.8.0.dist-info/METADATA
code2prompt-0.8.0.dist-info/WHEEL
code2prompt-0.8.0.dist-info/entry_points.txt
code2prompt-0.8.0.dist-info/RECORD
